{
  "version": "7",
  "dialect": "mysql",
  "entries": [
    {
      "idx": 0,
      "version": "5",
      "when": 1769540186099,
      "tag": "0000_quiet_blink",
      "breakpoints": true
    },
    {
      "idx": 1,
      "version": "5",
      "when": 1769540351007,
      "tag": "0001_hard_redwing",
      "breakpoints": true
    },
    {
      "idx": 2,
      "version": "5",
      "when": 1769541330229,
      "tag": "0002_cheerful_rattler",
      "breakpoints": true
    },
    {
      "idx": 3,
      "version": "5",
      "when": 1769543769095,
      "tag": "0003_little_leper_queen",
      "breakpoints": true
    },
    {
      "idx": 4,
      "version": "5",
      "when": 1769552252357,
      "tag": "0004_glossy_shinobi_shaw",
      "breakpoints": true
    },
    {
      "idx": 5,
      "version": "5",
      "when": 1769563306003,
      "tag": "0005_familiar_zaladane",
      "breakpoints": true
    },
    {
      "idx": 6,
      "version": "5",
      "when": 1769790945321,
      "tag": "0006_youthful_boomer",
      "breakpoints": true
    },
    {
      "idx": 7,
      "version": "5",
      "when": 1769791637975,
      "tag": "0007_burly_smasher",
      "breakpoints": true
    },
    {
      "idx": 8,
      "version": "5",
      "when": 1769803519091,
      "tag": "0008_pink_kate_bishop",
      "breakpoints": true
    },
    {
      "idx": 9,
      "version": "5",
      "when": 1770941178196,
      "tag": "0009_amused_sabretooth",
      "breakpoints": true
    },
    {
      "idx": 10,
      "version": "5",
      "when": 1770947843141,
      "tag": "0010_round_cardiac",
      "breakpoints": true
    },
    {
      "idx": 11,
      "version": "5",
      "when": 1770989388952,
      "tag": "0011_massive_adam_warlock",
      "breakpoints": true
    },
    {
      "idx": 12,
      "version": "5",
      "when": 1770992611827,
      "tag": "0012_supreme_dazzler",
      "breakpoints": true
    },
    {
      "idx": 13,
      "version": "5",
      "when": 1771000311562,
      "tag": "0013_damp_menace",
      "breakpoints": true
    },
    {
      "idx": 14,
      "version": "5",
      "when": 1771002524194,
      "tag": "0014_bent_yellowjacket",
      "breakpoints": true
    },
    {
      "idx": 15,
      "version": "5",
      "when": 1771011408283,
      "tag": "0015_open_rictor",
      "breakpoints": true
    },
    {
      "idx": 16,
      "version": "5",
      "when": 1771961319409,
      "tag": "0016_wet_alex_power",
      "breakpoints": true
    },
    {
      "idx": 17,
      "version": "5",
      "when": 1772156777008,
      "tag": "0017_nebulous_praxagora",
      "breakpoints": true
    },
    {
      "idx": 18,
      "version": "5",
      "when": 1772158758209,
      "tag": "0018_bent_vengeance",
      "breakpoints": true
    },
    {
      "idx": 19,
      "version": "5",
      "when": 1772160397056,
      "tag": "0019_colossal_vampiro",
      "breakpoints": true
    },
    {
      "idx": 20,
      "version": "5",
      "when": 1772161447645,
      "tag": "0020_supreme_blade",
      "breakpoints": true
    },
    {
      "idx": 21,
      "version": "5",
      "when": 1772227035763,
      "tag": "0021_regular_eddie_brock",
      "breakpoints": true
    },
    {
      "idx": 22,
      "version": "5",
      "when": 1772229369968,
      "tag": "0022_thin_shooting_star",
      "breakpoints": true
    }
  ]
}