{
  "query": "\nSELECT \n  ms.id AS sessao_id,\n  ms.sessionDate,\n  ms.sessionNumber,\n  ms.presence,\n  ms.alunoId,\n  a.name AS aluno_nome,\n  ms.consultorId,\n  c.name AS mentor_nome,\n  p.name AS empresa_nome,\n  (SELECT ma.id FROM mentor_appointments ma\n   JOIN appointment_participants ap ON ap.appointmentId = ma.id\n   WHERE ma.consultorId = ms.consultorId\n   AND ma.scheduledDate = ms.sessionDate\n   AND ap.alunoId = ms.alunoId\n   AND ma.status != 'cancelado'\n   LIMIT 1) AS agendamento_id,\n  (SELECT ma.status FROM mentor_appointments ma\n   JOIN appointment_participants ap ON ap.appointmentId = ma.id\n   WHERE ma.consultorId = ms.consultorId\n   AND ma.scheduledDate = ms.sessionDate\n   AND ap.alunoId = ms.alunoId\n   LIMIT 1) AS agendamento_status\nFROM mentoring_sessions ms\nLEFT JOIN alunos a ON ms.alunoId = a.id\nLEFT JOIN consultors c ON ms.consultorId = c.id\nLEFT JOIN programs p ON a.programId = p.id\nWHERE ms.sessionDate >= '2026-03-01' AND ms.sessionDate <= '2026-03-31'\nORDER BY ms.consultorId, ms.sessionDate, a.name\nLIMIT 20;\n",
  "command": "mysql --batch --raw --column-names --default-character-set=utf8mb4 --host gateway02.us-east-1.prod.aws.tidbcloud.com --port 4000 --user 2kPX7CjhqdMFT8y.9c22f9f54902 --database 5n7arrGNHjNdoFCMzyGXcY --execute \nSELECT \n  ms.id AS sessao_id,\n  ms.sessionDate,\n  ms.sessionNumber,\n  ms.presence,\n  ms.alunoId,\n  a.name AS aluno_nome,\n  ms.consultorId,\n  c.name AS mentor_nome,\n  p.name AS empresa_nome,\n  (SELECT ma.id FROM mentor_appointments ma\n   JOIN appointment_participants ap ON ap.appointmentId = ma.id\n   WHERE ma.consultorId = ms.consultorId\n   AND ma.scheduledDate = ms.sessionDate\n   AND ap.alunoId = ms.alunoId\n   AND ma.status != 'cancelado'\n   LIMIT 1) AS agendamento_id,\n  (SELECT ma.status FROM mentor_appointments ma\n   JOIN appointment_participants ap ON ap.appointmentId = ma.id\n   WHERE ma.consultorId = ms.consultorId\n   AND ma.scheduledDate = ms.sessionDate\n   AND ap.alunoId = ms.alunoId\n   LIMIT 1) AS agendamento_status\nFROM mentoring_sessions ms\nLEFT JOIN alunos a ON ms.alunoId = a.id\nLEFT JOIN consultors c ON ms.consultorId = c.id\nLEFT JOIN programs p ON a.programId = p.id\nWHERE ms.sessionDate >= '2026-03-01' AND ms.sessionDate <= '2026-03-31'\nORDER BY ms.consultorId, ms.sessionDate, a.name\nLIMIT 20;\n",
  "rows": [
    {
      "sessao_id": "180017",
      "sessionDate": "2026-03-16",
      "sessionNumber": "17",
      "presence": "presente",
      "alunoId": "30020",
      "aluno_nome": "Adrielle De Araújo Santos Bessa",
      "consultorId": "28",
      "mentor_nome": "Ana Carolina Cardoso Viana Rocha",
      "empresa_nome": "SEBRAE ACRE",
      "agendamento_id": "120010",
      "agendamento_status": "agendado"
    },
    {
      "sessao_id": "180010",
      "sessionDate": "2026-03-16",
      "sessionNumber": "17",
      "presence": "ausente",
      "alunoId": "30021",
      "aluno_nome": "Aldemar Dos Santos Maciel",
      "consultorId": "28",
      "mentor_nome": "Ana Carolina Cardoso Viana Rocha",
      "empresa_nome": "SEBRAE ACRE",
      "agendamento_id": "120010",
      "agendamento_status": "agendado"
    },
    {
      "sessao_id": "180007",
      "sessionDate": "2026-03-16",
      "sessionNumber": "17",
      "presence": "presente",
      "alunoId": "30011",
      "aluno_nome": "Claudia Maia Da Silva",
      "consultorId": "28",
      "mentor_nome": "Ana Carolina Cardoso Viana Rocha",
      "empresa_nome": "SEBRAE ACRE",
      "agendamento_id": "120010",
      "agendamento_status": "agendado"
    },
    {
      "sessao_id": "180005",
      "sessionDate": "2026-03-16",
      "sessionNumber": "17",
      "presence": "presente",
      "alunoId": "30003",
      "aluno_nome": "Hellen Kelma Araújo Chaves",
      "consultorId": "28",
      "mentor_nome": "Ana Carolina Cardoso Viana Rocha",
      "empresa_nome": "SEBRAE ACRE",
      "agendamento_id": "120010",
      "agendamento_status": "agendado"
    },
    {
      "sessao_id": "180006",
      "sessionDate": "2026-03-16",
      "sessionNumber": "17",
      "presence": "presente",
      "alunoId": "30008",
      "aluno_nome": "Izabel Cristina De Oliveira Barros",
      "consultorId": "28",
      "mentor_nome": "Ana Carolina Cardoso Viana Rocha",
      "empresa_nome": "SEBRAE ACRE",
      "agendamento_id": "120010",
      "agendamento_status": "agendado"
    },
    {
      "sessao_id": "180009",
      "sessionDate": "2026-03-16",
      "sessionNumber": "17",
      "presence": "ausente",
      "alunoId": "30018",
      "aluno_nome": "Jailson Barbosa De Araújo",
      "consultorId": "28",
      "mentor_nome": "Ana Carolina Cardoso Viana Rocha",
      "empresa_nome": "SEBRAE ACRE",
      "agendamento_id": "120010",
      "agendamento_status": "agendado"
    },
    {
      "sessao_id": "180008",
      "sessionDate": "2026-03-16",
      "sessionNumber": "17",
      "presence": "ausente",
      "alunoId": "30004",
      "aluno_nome": "Joelma Da Silva Mourão",
      "consultorId": "28",
      "mentor_nome": "Ana Carolina Cardoso Viana Rocha",
      "empresa_nome": "SEBRAE ACRE",
      "agendamento_id": "120010",
      "agendamento_status": "agendado"
    },
    {
      "sessao_id": "180004",
      "sessionDate": "2026-03-16",
      "sessionNumber": "17",
      "presence": "presente",
      "alunoId": "30007",
      "aluno_nome": "Natana Dourado Sousa",
      "consultorId": "28",
      "mentor_nome": "Ana Carolina Cardoso Viana Rocha",
      "empresa_nome": "SEBRAE ACRE",
      "agendamento_id": "120010",
      "agendamento_status": "agendado"
    },
    {
      "sessao_id": "240001",
      "sessionDate": "2026-03-18",
      "sessionNumber": "17",
      "presence": "ausente",
      "alunoId": "30033",
      "aluno_nome": "Adonay Fares Custódio Dos Santos",
      "consultorId": "28",
      "mentor_nome": "Ana Carolina Cardoso Viana Rocha",
      "empresa_nome": "SEBRAE ACRE",
      "agendamento_id": "120007",
      "agendamento_status": "agendado"
    },
    {
      "sessao_id": "180014",
      "sessionDate": "2026-03-18",
      "sessionNumber": "17",
      "presence": "presente",
      "alunoId": "30012",
      "aluno_nome": "Adriana Elizabete De Souza Dantas",
      "consultorId": "28",
      "mentor_nome": "Ana Carolina Cardoso Viana Rocha",
      "empresa_nome": "SEBRAE ACRE",
      "agendamento_id": "120007",
      "agendamento_status": "agendado"
    },
    {
      "sessao_id": "270005",
      "sessionDate": "2026-03-18",
      "sessionNumber": "17",
      "presence": "ausente",
      "alunoId": "30024",
      "aluno_nome": "Francinei Do Socorro Lima Dos Santos",
      "consultorId": "28",
      "mentor_nome": "Ana Carolina Cardoso Viana Rocha",
      "empresa_nome": "SEBRAE ACRE",
      "agendamento_id": "120007",
      "agendamento_status": "agendado"
    },
    {
      "sessao_id": "180013",
      "sessionDate": "2026-03-18",
      "sessionNumber": "17",
      "presence": "presente",
      "alunoId": "30014",
      "aluno_nome": "Janaina Feitosa",
      "consultorId": "28",
      "mentor_nome": "Ana Carolina Cardoso Viana Rocha",
      "empresa_nome": "SEBRAE ACRE",
      "agendamento_id": "120007",
      "agendamento_status": "agendado"
    },
    {
      "sessao_id": "240002",
      "sessionDate": "2026-03-18",
      "sessionNumber": "17",
      "presence": "ausente",
      "alunoId": "30026",
      "aluno_nome": "Jersey James Da Costa",
      "consultorId": "28",
      "mentor_nome": "Ana Carolina Cardoso Viana Rocha",
      "empresa_nome": "SEBRAE ACRE",
      "agendamento_id": "120007",
      "agendamento_status": "agendado"
    },
    {
      "sessao_id": "180016",
      "sessionDate": "2026-03-18",
      "sessionNumber": "17",
      "presence": "presente",
      "alunoId": "30015",
      "aluno_nome": "Katiele Siqueira Maia",
      "consultorId": "28",
      "mentor_nome": "Ana Carolina Cardoso Viana Rocha",
      "empresa_nome": "SEBRAE ACRE",
      "agendamento_id": "120007",
      "agendamento_status": "agendado"
    },
    {
      "sessao_id": "180003",
      "sessionDate": "2026-03-18",
      "sessionNumber": "7",
      "presence": "presente",
      "alunoId": "30098",
      "aluno_nome": "Luciana Carvalho de Aguiar",
      "consultorId": "28",
      "mentor_nome": "Ana Carolina Cardoso Viana Rocha",
      "empresa_nome": "SEBRAE TO",
      "agendamento_id": "120005",
      "agendamento_status": "confirmado"
    },
    {
      "sessao_id": "180015",
      "sessionDate": "2026-03-18",
      "sessionNumber": "17",
      "presence": "presente",
      "alunoId": "30030",
      "aluno_nome": "Marinete Lourdes Araujo De Queiroz",
      "consultorId": "28",
      "mentor_nome": "Ana Carolina Cardoso Viana Rocha",
      "empresa_nome": "SEBRAE ACRE",
      "agendamento_id": "120007",
      "agendamento_status": "agendado"
    },
    {
      "sessao_id": "180002",
      "sessionDate": "2026-03-18",
      "sessionNumber": "7",
      "presence": "presente",
      "alunoId": "30094",
      "aluno_nome": "Mirelle Soares Milhomens",
      "consultorId": "28",
      "mentor_nome": "Ana Carolina Cardoso Viana Rocha",
      "empresa_nome": "SEBRAE TO",
      "agendamento_id": "120005",
      "agendamento_status": "confirmado"
    },
    {
      "sessao_id": "180011",
      "sessionDate": "2026-03-18",
      "sessionNumber": "17",
      "presence": "presente",
      "alunoId": "30005",
      "aluno_nome": "Miriam Nazareth Cardenas Moreno",
      "consultorId": "28",
      "mentor_nome": "Ana Carolina Cardoso Viana Rocha",
      "empresa_nome": "SEBRAE ACRE",
      "agendamento_id": "120007",
      "agendamento_status": "agendado"
    },
    {
      "sessao_id": "180012",
      "sessionDate": "2026-03-18",
      "sessionNumber": "17",
      "presence": "presente",
      "alunoId": "30016",
      "aluno_nome": "Sônia Caroline Suárez da Costa Pinheiro",
      "consultorId": "28",
      "mentor_nome": "Ana Carolina Cardoso Viana Rocha",
      "empresa_nome": "SEBRAE ACRE",
      "agendamento_id": "120007",
      "agendamento_status": "agendado"
    },
    {
      "sessao_id": "180001",
      "sessionDate": "2026-03-18",
      "sessionNumber": "7",
      "presence": "presente",
      "alunoId": "30097",
      "aluno_nome": "Wandemberg Pereira Rodrigues",
      "consultorId": "28",
      "mentor_nome": "Ana Carolina Cardoso Viana Rocha",
      "empresa_nome": "SEBRAE TO",
      "agendamento_id": "120005",
      "agendamento_status": "confirmado"
    }
  ],
  "messages": [],
  "stdout": "sessao_id\tsessionDate\tsessionNumber\tpresence\talunoId\taluno_nome\tconsultorId\tmentor_nome\tempresa_nome\tagendamento_id\tagendamento_status\n180017\t2026-03-16\t17\tpresente\t30020\tAdrielle De Araújo Santos Bessa\t28\tAna Carolina Cardoso Viana Rocha\tSEBRAE ACRE\t120010\tagendado\n180010\t2026-03-16\t17\tausente\t30021\tAldemar Dos Santos Maciel\t28\tAna Carolina Cardoso Viana Rocha\tSEBRAE ACRE\t120010\tagendado\n180007\t2026-03-16\t17\tpresente\t30011\tClaudia Maia Da Silva\t28\tAna Carolina Cardoso Viana Rocha\tSEBRAE ACRE\t120010\tagendado\n180005\t2026-03-16\t17\tpresente\t30003\tHellen Kelma Araújo Chaves\t28\tAna Carolina Cardoso Viana Rocha\tSEBRAE ACRE\t120010\tagendado\n180006\t2026-03-16\t17\tpresente\t30008\tIzabel Cristina De Oliveira Barros\t28\tAna Carolina Cardoso Viana Rocha\tSEBRAE ACRE\t120010\tagendado\n180009\t2026-03-16\t17\tausente\t30018\tJailson Barbosa De Araújo\t28\tAna Carolina Cardoso Viana Rocha\tSEBRAE ACRE\t120010\tagendado\n180008\t2026-03-16\t17\tausente\t30004\tJoelma Da Silva Mourão\t28\tAna Carolina Cardoso Viana Rocha\tSEBRAE ACRE\t120010\tagendado\n180004\t2026-03-16\t17\tpresente\t30007\tNatana Dourado Sousa\t28\tAna Carolina Cardoso Viana Rocha\tSEBRAE ACRE\t120010\tagendado\n240001\t2026-03-18\t17\tausente\t30033\tAdonay Fares Custódio Dos Santos\t28\tAna Carolina Cardoso Viana Rocha\tSEBRAE ACRE\t120007\tagendado\n180014\t2026-03-18\t17\tpresente\t30012\tAdriana Elizabete De Souza Dantas\t28\tAna Carolina Cardoso Viana Rocha\tSEBRAE ACRE\t120007\tagendado\n270005\t2026-03-18\t17\tausente\t30024\tFrancinei Do Socorro Lima Dos Santos\t28\tAna Carolina Cardoso Viana Rocha\tSEBRAE ACRE\t120007\tagendado\n180013\t2026-03-18\t17\tpresente\t30014\tJanaina Feitosa\t28\tAna Carolina Cardoso Viana Rocha\tSEBRAE ACRE\t120007\tagendado\n240002\t2026-03-18\t17\tausente\t30026\tJersey James Da Costa\t28\tAna Carolina Cardoso Viana Rocha\tSEBRAE ACRE\t120007\tagendado\n180016\t2026-03-18\t17\tpresente\t30015\tKatiele Siqueira Maia\t28\tAna Carolina Cardoso Viana Rocha\tSEBRAE ACRE\t120007\tagendado\n180003\t2026-03-18\t7\tpresente\t30098\tLuciana Carvalho de Aguiar\t28\tAna Carolina Cardoso Viana Rocha\tSEBRAE TO\t120005\tconfirmado\n180015\t2026-03-18\t17\tpresente\t30030\tMarinete Lourdes Araujo De Queiroz\t28\tAna Carolina Cardoso Viana Rocha\tSEBRAE ACRE\t120007\tagendado\n180002\t2026-03-18\t7\tpresente\t30094\tMirelle Soares Milhomens\t28\tAna Carolina Cardoso Viana Rocha\tSEBRAE TO\t120005\tconfirmado\n180011\t2026-03-18\t17\tpresente\t30005\tMiriam Nazareth Cardenas Moreno\t28\tAna Carolina Cardoso Viana Rocha\tSEBRAE ACRE\t120007\tagendado\n180012\t2026-03-18\t17\tpresente\t30016\tSônia Caroline Suárez da Costa Pinheiro\t28\tAna Carolina Cardoso Viana Rocha\tSEBRAE ACRE\t120007\tagendado\n180001\t2026-03-18\t7\tpresente\t30097\tWandemberg Pereira Rodrigues\t28\tAna Carolina Cardoso Viana Rocha\tSEBRAE TO\t120005\tconfirmado\n",
  "stderr": "",
  "execution_time_ms": 133
}